{
  "owner": "googleworkspace-bot",
  "slug": "recipe-create-presentation",
  "displayName": "Recipe Create Presentation",
  "latest": {
    "version": "1.0.10",
    "publishedAt": 1774551134351,
    "commit": "https://github.com/openclaw/skills/commit/85b45b6f1e03e5a5f8305ab8c85dca61134fd409"
  },
  "history": [
    {
      "version": "1.0.1",
      "publishedAt": 1774300593674,
      "commit": "https://github.com/openclaw/skills/commit/f21b42f52be0e125f658b05bc16e8cfb7c4de521"
    },
    {
      "version": "1.0.0",
      "publishedAt": 1772933764850,
      "commit": "https://github.com/openclaw/skills/commit/3c63f5ac81fe90e1c5e174493c6b603e95866b3d"
    }
  ]
}
