{
  "id": "8479eda7",
  "created_at": "2026-02-22T05:00:32.180230+00:00",
  "status": "deployed",
  "priority": "critical",
  "mutation_type": "repair",
  "pattern": {
    "category": "other",
    "task_type": "unknown",
    "issue": "wal_miss"
  },
  "title": "Address 'wal_miss' in 'unknown' tasks",
  "description": "In 'unknown' tasks, 'wal_miss' occurs 1x with 100% failure rate",
  "action_type": "update_agents",
  "implementation": {
    "target_file": "AGENTS.md",
    "changes": "Investigate and document fix for: In 'unknown' tasks, 'wal_miss' occurs 1x with 100% failure rate",
    "estimated_effort": 30
  },
  "validation_criteria": [
    "Issue frequency drops by >50%"
  ],
  "expected_improvement": "Reduce failure rate and improve quality score",
  "duplicate_count": 160,
  "last_seen": "2026-03-01T20:30:30.046526+00:00",
  "safe_category": false,
  "frequency": 7,
  "deployed_at": "2026-02-22T17:00:00Z",
  "notes": "Resolved: PyPI token encrypted and stored. WAL discipline logged."
}